{
  "hash": "82c49dff",
  "browserHash": "601fffa4",
  "optimized": {
    "vue": {
      "src": "../../../../node_modules/vue/dist/vue.runtime.esm-browser.js",
      "file": "vue.js",
      "fileHash": "31155e98",
      "needsInterop": false
    },
    "vitepress > @vue/devtools-api": {
      "src": "../../../../node_modules/@vue/devtools-api/lib/esm/index.js",
      "file": "vitepress___@vue_devtools-api.js",
      "fileHash": "a88463af",
      "needsInterop": false
    },
    "fire-starters": {
      "src": "../../../../node_modules/fire-starters/dist/library.mjs",
      "file": "fire-starters.js",
      "fileHash": "5a3af723",
      "needsInterop": false
    }
  },
  "chunks": {
    "chunk-TNURRTOV": {
      "file": "chunk-TNURRTOV.js"
    },
    "html2canvas.esm-A6VP4V3A": {
      "file": "html2canvas__esm-A6VP4V3A.js"
    },
    "purify.es-6L6XDMTV": {
      "file": "purify__es-6L6XDMTV.js"
    },
    "index.es-L2EOCMTW": {
      "file": "index__es-L2EOCMTW.js"
    },
    "chunk-HNBWJEJ2": {
      "file": "chunk-HNBWJEJ2.js"
    },
    "chunk-NUTPE2YY": {
      "file": "chunk-NUTPE2YY.js"
    }
  }
}